gitlab2zenodo/__init__.py
gitlab2zenodo/deposit.py
gitlab2zenodo/deposit_BACKUP_11389.py
gitlab2zenodo/deposit_BASE_11389.py
gitlab2zenodo/deposit_LOCAL_11389.py
gitlab2zenodo/deposit_REMOTE_11389.py
gitlab2zenodo/main.py
gitlab2zenodo/settings.py
tests/__init__.py
tests/test_gitlab2zenodo.py
tests/test_main.py
tests/test_settings.py
gitlab2zenodo-0.0b7.dist-info/LICENSE
gitlab2zenodo-0.0b7.dist-info/METADATA
gitlab2zenodo-0.0b7.dist-info/WHEEL
gitlab2zenodo-0.0b7.dist-info/entry_points.txt
gitlab2zenodo-0.0b7.dist-info/top_level.txt
gitlab2zenodo-0.0b7.dist-info/RECORD
