Metadata-Version: 2.1
Name: gitlab2zenodo
Version: 0.0b7
Summary: Sends gitlab snapshots to zenodo Automatically.
Home-page: https://gitlab.com/sbeniamine/gitlab2zenodo
Author: Sacha Beniamine
License: Apache License Version 2.0
Keywords: zenodo gitlab
Platform: UNKNOWN
Classifier: Development Status :: 4 - Beta
Classifier: Intended Audience :: Developers
Classifier: Intended Audience :: Science/Research
Classifier: License :: OSI Approved :: Apache Software License
Classifier: Operating System :: OS Independent
Classifier: Programming Language :: Python :: 3
Classifier: Programming Language :: Python :: 3.5
Classifier: Programming Language :: Python :: 3.6
Classifier: Programming Language :: Python :: 3.7
Requires-Python: >=3.5
License-File: LICENSE
Requires-Dist: requests
Requires-Dist: responses
